jentic/apitools/openapi/datamodels/low/__init__.py
jentic/apitools/openapi/datamodels/low/context.py
jentic/apitools/openapi/datamodels/low/extractors.py
jentic/apitools/openapi/datamodels/low/fields.py
jentic/apitools/openapi/datamodels/low/py.typed
jentic/apitools/openapi/datamodels/low/sources.py
jentic/apitools/openapi/datamodels/low/v30/__init__.py
jentic/apitools/openapi/datamodels/low/v30/builders/__init__.py
jentic/apitools/openapi/datamodels/low/v30/callback.py
jentic/apitools/openapi/datamodels/low/v30/components.py
jentic/apitools/openapi/datamodels/low/v30/contact.py
jentic/apitools/openapi/datamodels/low/v30/discriminator.py
jentic/apitools/openapi/datamodels/low/v30/encoding.py
jentic/apitools/openapi/datamodels/low/v30/example.py
jentic/apitools/openapi/datamodels/low/v30/external_documentation.py
jentic/apitools/openapi/datamodels/low/v30/header.py
jentic/apitools/openapi/datamodels/low/v30/info.py
jentic/apitools/openapi/datamodels/low/v30/license.py
jentic/apitools/openapi/datamodels/low/v30/link.py
jentic/apitools/openapi/datamodels/low/v30/media_type.py
jentic/apitools/openapi/datamodels/low/v30/oauth_flow.py
jentic/apitools/openapi/datamodels/low/v30/oauth_flows.py
jentic/apitools/openapi/datamodels/low/v30/openapi.py
jentic/apitools/openapi/datamodels/low/v30/operation.py
jentic/apitools/openapi/datamodels/low/v30/parameter.py
jentic/apitools/openapi/datamodels/low/v30/path_item.py
jentic/apitools/openapi/datamodels/low/v30/paths.py
jentic/apitools/openapi/datamodels/low/v30/reference.py
jentic/apitools/openapi/datamodels/low/v30/request_body.py
jentic/apitools/openapi/datamodels/low/v30/response.py
jentic/apitools/openapi/datamodels/low/v30/responses.py
jentic/apitools/openapi/datamodels/low/v30/schema.py
jentic/apitools/openapi/datamodels/low/v30/security_requirement.py
jentic/apitools/openapi/datamodels/low/v30/security_scheme.py
jentic/apitools/openapi/datamodels/low/v30/server.py
jentic_openapi_datamodels-1.0.0a34.dist-info/licenses/LICENSE
jentic_openapi_datamodels-1.0.0a34.dist-info/licenses/NOTICE
jentic_openapi_datamodels-1.0.0a34.dist-info/WHEEL
jentic_openapi_datamodels-1.0.0a34.dist-info/METADATA
jentic_openapi_datamodels-1.0.0a34.dist-info/RECORD
